setup.py
xxlib/xxlibnews.py
xxlib/xxlibprint.py
xxlib/xxlibpy.py
xxlib/xxlibsearch.py
xxlib.egg-info/PKG-INFO
xxlib.egg-info/SOURCES.txt
xxlib.egg-info/dependency_links.txt
xxlib.egg-info/top_level.txt