Metadata-Version: 1.0
Name: xxlib
Version: 1.7.0
Summary: 轩轩库，轩轩工作室-轩轩制作，翻版、抄袭必究
Home-page: http://cyxxxw.byethost18.com/
Author: 轩轩
Author-email: 3603695237@qq.com
License: UNKNOWN
Platform: UNKNOWN
